asucks/server.py
asucks-0.2.0.dist-info/LICENSE
asucks-0.2.0.dist-info/WHEEL
asucks-0.2.0.dist-info/METADATA
asucks-0.2.0.dist-info/RECORD
