Metadata-Version: 2.1
Name: asucks
Version: 0.2.0
Summary: SOCKS5 async python server
Author: Gabriel Tincu
Author-email: gabi@aiven.io
Requires-Python: >=3.7,<4.0
Classifier: Programming Language :: Python :: 3
Classifier: Programming Language :: Python :: 3.7
Classifier: Programming Language :: Python :: 3.8
Requires-Dist: aiohttp (==3.7.2)
Requires-Dist: click (==7.1.2)
